{
  "id": "1824",
  "family_name": "ITC_Conduit®_OT_Pro",
  "font_families": [
    "ConduitITCPro-ExtraBoldItalic",
    "ConduitITCPro-BoldItalic",
    "ConduitITCPro-Regular",
    "ConduitITCPro-ExtraLightItalic",
    "ConduitITCPro-MediumItalic",
    "ConduitITCPro-Bold",
    "ConduitITCPro-BlackItalic",
    "ConduitITCPro-Medium",
    "ConduitITCPro-LightItalic",
    "ConduitITCPro-Italic",
    "ConduitITCPro-Black",
    "ConduitITCPro-ExtraLight",
    "ConduitITCPro-ExtraBold",
    "ConduitITCPro-Light"
  ],
  "url": "https://lets.fontworks.co.jp/fonts/1824",
  "fonts_saved": []
}